{
    "kind": "youtube#videoListResponse",
    "etag": "a4tOyoaduq4S762njzgOfIqOrXg",
    "items": [
        {
            "kind": "youtube#video",
            "etag": "TKm9Qzc3USU6PPY5cIy5fk4cCxQ",
            "id": "jiJu4K2jems",
            "snippet": {
                "publishedAt": "2021-02-03T19:55:13Z",
                "channelId": "UCH5fn41ZeWuJtJhxdjqJ9tw",
                "title": "Demon slayer op (look in desc)",
                "description": "I do not own this so pls do not copyright",
                "thumbnails": {
                    "default": {
                        "url": "https://i.ytimg.com/vi/jiJu4K2jems/default.jpg",
                        "width": 120,
                        "height": 90
                    },
                    "medium": {
                        "url": "https://i.ytimg.com/vi/jiJu4K2jems/mqdefault.jpg",
                        "width": 320,
                        "height": 180
                    },
                    "high": {
                        "url": "https://i.ytimg.com/vi/jiJu4K2jems/hqdefault.jpg",
                        "width": 480,
                        "height": 360
                    },
                    "standard": {
                        "url": "https://i.ytimg.com/vi/jiJu4K2jems/sddefault.jpg",
                        "width": 640,
                        "height": 480
                    },
                    "maxres": {
                        "url": "https://i.ytimg.com/vi/jiJu4K2jems/maxresdefault.jpg",
                        "width": 1280,
                        "height": 720
                    }
                },
                "channelTitle": "Tanjiro Kamado",
                "categoryId": "22",
                "liveBroadcastContent": "none",
                "localized": {
                    "title": "Demon slayer op (look in desc)",
                    "description": "I do not own this so pls do not copyright"
                }
            },
            "contentDetails": {
                "duration": "PT1M30S",
                "dimension": "2d",
                "definition": "hd",
                "caption": "false",
                "licensedContent": false,
                "contentRating": {},
                "projection": "rectangular"
            },
            "statistics": {
                "viewCount": "8450531",
                "likeCount": "162315",
                "favoriteCount": "0",
                "commentCount": "5237"
            }
        }
    ],
    "pageInfo": {
        "totalResults": 1,
        "resultsPerPage": 1
    }
}